{
	"pools": [
		{
			"name": "main",
			"rolls": {
				"min": 1,
				"max": 2
			},
			"entries": [
				{
					"type": "item",
					"name": "losteclipse:malachiteIngot",
					"weight": 4,
					"functions": [
						{
							"function": "set_count",
							"count": {
								"min": 0,
								"max": 1
							}
						}
					]
				},
				{
					"type": "item",
					"name": "losteclipse:soulGemFragment",
					"weight": 4,
					"functions": [
						{
							"function": "set_count",
							"count": {
								"min": 1,
								"max": 2
							}
						}
					]
				},
				{
					"type": "item",
					"name": "losteclipse:garnet",
					"weight": 5
				},
				{
					"type": "item",
					"name": "losteclipse:fireGlyph",
					"weight": 4
				},
				{
					"type": "item",
					"name": "losteclipse:frostGlyph",
					"weight": 4
				},
				{
					"type": "item",
					"name": "losteclipse:poisonGlyph",
					"weight": 4
				},
				{
					"type": "item",
					"name": "losteclipse:strengthGlyph",
					"weight": 3
				},
				{
					"type": "item",
					"name": "losteclipse:minorDamageGlyph",
					"weight": 3
				},
				{
					"type": "item",
					"name": "losteclipse:minorEtherealGlyph",
					"weight": 3
				},
				{
					"type": "item",
					"name": "losteclipse:hardenedGlyph",
					"weight": 3
				},
				{
					"type": "item",
					"name": "losteclipse:fireballScroll",
					"weight": 2
				},
				{
					"type": "item",
					"name": "losteclipse:frostbiteScroll",
					"weight": 2
				},
				{
					"type": "item",
					"name": "losteclipse:hardenedScroll",
					"weight": 2
				}
			]
		}
	]
}	